{
  "base": {
    "primary": {
      "50": {
        "value": "{core.color.palette.brandprim.50}",
        "type": "color"
      },
      "100": {
        "value": "{core.color.palette.brandprim.100}",
        "type": "color"
      },
      "200": {
        "value": "{core.color.palette.brandprim.200}",
        "type": "color"
      },
      "300": {
        "value": "{core.color.palette.brandprim.300}",
        "type": "color"
      },
      "400": {
        "value": "{core.color.palette.brandprim.400}",
        "type": "color"
      }
    }
  }
}